[
  {
    "id": 1,
    "front": "Why did post-Ice Age geography matter so much in Norway?",
    "back": "It produced fjords, coasts, and difficult terrain that favored maritime livelihoods and regional fragmentation."
  },
  {
    "id": 2,
    "front": "What changed when farming reached Norway around 4000 BCE?",
    "back": "Farming was added, but many communities kept mixed economies because climate and terrain limited agriculture."
  },
  {
    "id": 3,
    "front": "How did Bronze Age trade shape Norway?",
    "back": "Because bronze had to be imported, trade links and seafaring skills became more important."
  },
  {
    "id": 4,
    "front": "What social groups existed in Iron Age Norse society?",
    "back": "Chieftains, free farmers, and slaves, with power mostly local and personal."
  },
  {
    "id": 5,
    "front": "What made the longship a strategic breakthrough?",
    "back": "Its speed and shallow draft allowed both ocean crossings and river movement."
  },
  {
    "id": 6,
    "front": "Why is Lindisfarne (793) historically symbolic?",
    "back": "It became a famous marker of Viking expansion in Western Europe."
  },
  {
    "id": 7,
    "front": "How are unification and Iceland settlement connected?",
    "back": "Some elites and followers left Norway rather than submit to central royal control."
  },
  {
    "id": 8,
    "front": "What broader shift is linked to 1066?",
    "back": "From Viking expansion politics toward Christian medieval monarchy and administration."
  }
]